langesim/__init__.py
langesim/graphic_utilities.py
langesim/sampler.py
langesim/simulator.py
langesim-0.1.4.dist-info/LICENCE
langesim-0.1.4.dist-info/METADATA
langesim-0.1.4.dist-info/WHEEL
langesim-0.1.4.dist-info/RECORD
